datavis_cli/__init__.py
datavis_cli/__main__.py
datavis_cli-0.1.3.dist-info/METADATA
datavis_cli-0.1.3.dist-info/WHEEL
datavis_cli-0.1.3.dist-info/entry_points.txt
datavis_cli-0.1.3.dist-info/RECORD
